skautobots/__init__.py
skautobots/date_processing/__init__.py
skautobots/date_processing/_date_fourier.py
skautobots/date_processing/_date_linear.py
sk_autobots-0.0.4.dist-info/LICENSE
sk_autobots-0.0.4.dist-info/METADATA
sk_autobots-0.0.4.dist-info/WHEEL
sk_autobots-0.0.4.dist-info/top_level.txt
sk_autobots-0.0.4.dist-info/RECORD
