Metadata-Version: 2.1
Name: sk-autobots
Version: 0.0.4
Summary: Custom data transformers that use the scikit-learn API.
Home-page: https://github.com/ccastleberry/sk-autobots
Author: Caleb Castleberry
Author-email: castle.caleb@gmail.com
License: UNKNOWN
Platform: UNKNOWN
Classifier: Programming Language :: Python :: 3
Classifier: License :: OSI Approved :: MIT License
Classifier: Operating System :: OS Independent
Requires-Python: >=3.7
